{
  "kind": "collectionType",
  "collectionName": "members",
  "info": {
    "singularName": "member",
    "pluralName": "members",
    "displayName": "Members",
    "description": ""
  },
  "options": {
    "draftAndPublish": true
  },
  "pluginOptions": {},
  "attributes": {
    "Name": {
      "type": "string"
    },
    "Photo": {
      "type": "media",
      "multiple": false,
      "required": false,
      "allowedTypes": ["images", "files", "videos", "audios"]
    },
    "Bio": {
      "type": "customField",
      "options": {
        "preset": "defaultHtml"
      },
      "customField": "plugin::ckeditor5.CKEditor"
    },
    "Email": {
      "type": "email"
    },
    "LinkedIn": {
      "type": "string"
    },
    "BioImage": {
      "type": "media",
      "multiple": false,
      "required": false,
      "allowedTypes": ["images", "files", "videos", "audios"]
    },
    "SortOrder": {
      "type": "decimal"
    },
    "Tags": {
      "type": "customField",
      "options": ["SAMI", "AMI", "Trustee"],
      "customField": "plugin::multi-select.multi-select"
    }
  }
}
