[
  {
    "component_id": 1,
    "component_type": "home.hero-image",
    "entity_id": 1,
    "field": "HeroImages",
    "id": 33,
    "order": 1
  },
  {
    "component_id": 1,
    "component_type": "home.mission-statement",
    "entity_id": 1,
    "field": "MissionStatement",
    "id": 34,
    "order": 2
  },
  {
    "component_id": 1,
    "component_type": "home.project-summary",
    "entity_id": 1,
    "field": "ProjectSummary",
    "id": 35,
    "order": 3
  },
  {
    "component_id": 1,
    "component_type": "home.get-involved",
    "entity_id": 1,
    "field": "GetInvolved",
    "id": 36,
    "order": 4
  },
  {
    "component_id": 1,
    "component_type": "home.impact-section",
    "entity_id": 1,
    "field": "ImpactSection",
    "id": 37,
    "order": 5
  }
]
